Metadata-Version: 2.1
Name: saga-vcs
Version: 0.0.22
Summary: saga is a version control CLI that handles many file formats
Home-page: https://github.com/saga-vcs/saga
Author: saga
Author-email: narush@wharton.upenn.edu.com
License: UNKNOWN
Platform: UNKNOWN
Classifier: Programming Language :: Python :: 3
Requires-Python: >=3.6
Requires-Dist: XlsxWriter (>=1.2)
Requires-Dist: beautifulsoup4 (>=4.8)
Requires-Dist: html5lib (>=1.0)
Requires-Dist: requests (>-2.2)
